xml2df
